pymkv/ISO639_2.py
pymkv/MKVAttachment.py
pymkv/MKVFile.py
pymkv/MKVTrack.py
pymkv/Timestamp.py
pymkv/Verifications.py
pymkv/__init__.py
pymkv-1.0.8.dist-info/LICENSE.txt
pymkv-1.0.8.dist-info/METADATA
pymkv-1.0.8.dist-info/WHEEL
pymkv-1.0.8.dist-info/top_level.txt
pymkv-1.0.8.dist-info/RECORD
