Metadata-Version: 1.2
Name: pymkv
Version: 1.0.8
Summary: A Python wrapper for mkvmerge. It provides support for muxing, splitting, linking, chapters, tags, and attachments through the use of mkvmerge.
Home-page: https://github.com/sheldonkwoodward/pymkv
Author: Sheldon Woodward
Author-email: me@sheldonw.com
License: MIT
Keywords: wrapper
Platform: UNKNOWN
Classifier: Development Status :: 4 - Beta
Classifier: Intended Audience :: Developers
Classifier: License :: OSI Approved :: MIT License
Classifier: Natural Language :: English
Classifier: Operating System :: OS Independent
Classifier: Programming Language :: Python :: 3.6
Classifier: Programming Language :: Python :: 3.7
Classifier: Topic :: Multimedia :: Video :: Conversion
Classifier: Topic :: Utilities
Requires-Python: >=3.6
